cleverish/__init__.py
cleverish/_binaries.pyi
cleverish/drivers.py
cleverish/drivers.pyi
cleverish/main.py
cleverish/arguments/__init__.py
cleverish/arguments/add_analyse.py
cleverish/arguments/add_analyse.pyi
cleverish/arguments/definitions.py
cleverish/arguments/definitions.pyi
cleverish/arguments/pathways.py
cleverish/arguments/pathways.pyi
cleverish/exceptions/__init__.py
cleverish/exceptions/configuration_exceptions.py
cleverish/exceptions/configuration_exceptions.pyi
cleverish/exceptions/drivers.py
cleverish/exceptions/drivers.pyi
cleverish/exceptions/tomler_exceptions.py
cleverish/exceptions/tomler_exceptions.pyi
cleverish/utils/__init__.py
cleverish/utils/configure_.py
cleverish/utils/configure_.pyi
cleverish/utils/dotlock.py
cleverish/utils/dotlock.pyi
cleverish/utils/emulator.py
cleverish/utils/emulator.pyi
cleverish/utils/tomler_.py
cleverish/utils/tomler_.pyi
cleverish-0.0.3.dist-info/LICENSE
cleverish-0.0.3.dist-info/METADATA
cleverish-0.0.3.dist-info/WHEEL
cleverish-0.0.3.dist-info/entry_points.txt
cleverish-0.0.3.dist-info/top_level.txt
cleverish-0.0.3.dist-info/RECORD
