Metadata-Version: 2.1
Name: cleverish
Version: 0.0.3
Summary: Leave it to Cleverish, No more code breakage due to dependency. Dependency Handler
Author-email: Soumyo Deep Gupta <deep.main.ac@gmail.com>
Maintainer-email: Soumyo Deep Gupta <deep.main.ac@gmail.com>
License: MIT License
Project-URL: Documentation, https://d33p0st.in/documentation/libraries/cleverish/#libraries
Project-URL: GitHub, https://github.com/d33p0st/cleverish
Project-URL: Pull-Requests, https://github.com/d33p0st/cleverish/pulls
Project-URL: Issues, https://github.com/d33p0st/cleverish/pulls
Classifier: Development Status :: 4 - Beta
Classifier: Intended Audience :: Developers
Classifier: Topic :: Software Development :: Build Tools
Classifier: Programming Language :: Python :: 3.8
Classifier: Programming Language :: Python :: 3.9
Classifier: Programming Language :: Python :: 3.10
Classifier: Programming Language :: Python :: 3.11
Classifier: Programming Language :: Python :: 3.12
Classifier: Programming Language :: Python :: 3.13
Classifier: License :: OSI Approved :: MIT License
Classifier: Operating System :: MacOS :: MacOS X
Classifier: Operating System :: POSIX :: Linux
Classifier: Operating System :: Microsoft :: Windows
Classifier: Programming Language :: Python :: 3
Classifier: Programming Language :: Python :: 3 :: Only
Requires-Python: >=3.8
License-File: LICENSE
Requires-Dist: argpi==0.2.0
Requires-Dist: toml
Requires-Dist: colorama
Requires-Dist: prompt-toolkit
Requires-Dist: requests
